openinference/instrumentation/mistralai/__init__.py
openinference/instrumentation/mistralai/_chat_wrapper.py
openinference/instrumentation/mistralai/_request_attributes_extractor.py
openinference/instrumentation/mistralai/_response_accumulator.py
openinference/instrumentation/mistralai/_response_attributes_extractor.py
openinference/instrumentation/mistralai/_stream.py
openinference/instrumentation/mistralai/_utils.py
openinference/instrumentation/mistralai/_with_span.py
openinference/instrumentation/mistralai/package.py
openinference/instrumentation/mistralai/py.typed
openinference/instrumentation/mistralai/version.py
openinference_instrumentation_mistralai-1.3.4.dist-info/METADATA
openinference_instrumentation_mistralai-1.3.4.dist-info/WHEEL
openinference_instrumentation_mistralai-1.3.4.dist-info/entry_points.txt
openinference_instrumentation_mistralai-1.3.4.dist-info/licenses/LICENSE
openinference_instrumentation_mistralai-1.3.4.dist-info/RECORD
